{"type":"HOSTEL","name":"Tuatara Lodge","nameEN":"Tuatara Lodge","isActive":true,"isNew":false,"description":"Tuatara Lodge is a clean, warm, smoke free hostel with a friendly crew and excellent security. Our comfortable new accommodation includes bunks, doubles or executive ensuite rooms. All rooms are bright, spacious and warm with good ventilation. The multi-share room beds have hotel grade mattresses, mattress protectors, fitted bottom sheets and pillows with cases. \r\n\r\nOther popular facilities include a self-cater kitchen, two TV lounges, video, a bus stop at the front door, 24-hour guest access. Our reception is open from 2pm - 7pm daily.\r\n\r\nInvercargill is the last stop on the mainland for those visiting Stewart Island. It is a good starting point for discovering the Catlins or Fiordland via the Southern Scenic Route. Nearby you can also Walk the Hump Ridge Track, visit the Art Gallery, etc. Experience true southern hospitality.\r\n\r\nCheck in is 2 pm.  Check out is 10 am. Hostel facilities, e.g. showers, kitchen etc. are not to be used after 10 am check out.\r\n\r\nReception hours are 2.00pm - 7.00pm\r\nCheck-in hours are from 2pm to 7pm. Late check ins after 7pm must be made by prior arrangement.\r\n\r\nStrictly No alcohol allowed in the hostel.\r\n\r\nPayment for bookings is taken 48 hours prior to arrival.","hostelworldSays":null,"hostelSays":null,"location":{"address1":"30 - 32 Dee Street","address2":"P.O. Box 960","city":{"id":2081,"name":"Invercargill","nameEN":"Invercargill"},"country":{"id":151,"name":"New Zealand","nameEN":"New Zealand"},"region":{"id":138,"name":"Southland","nameEN":"Southland"},"latitude":"-46.4115012","longitude":"168.3469363","distance":{"kilometers":0.78,"miles":0.49}},"maxGuestsPerBooking":10,"depositPercentage":15,"ratings":{"security":82,"location":85,"staff":67,"atmosphere":53,"clean":75,"facilities":68,"value":75,"overall":72,"ratingsCount":636},"groupInformation":null,"currency":"NZD","houseRules":{"notes":"Check in is from 2 pm - 7 pm.  Check out is 10 am. Hostel facilities, e.g showers, kitchen etc are not to be used after 10 am check out.\r\n\r\nPayment for all bookings will be taken 48 hours prior to arrival - please ensure you have funds available on your credit card.\r\n\r\nReception hours are 2.00pm - 7pm\r\nCheck-in hours are from 2pm to 7pm\r\n\r\nPlease contact the hostel for any late check in after 7pm.\r\n\r\nStrictly No alcohol allowed in the hostel.  No persons under the age of 18.  No guests allowed in hostel.  No smoking/vaping.  No loud boom boxes.","checkin":{"from":14,"until":19},"latestCheckout":"10:00","policies":["AGERESTRICTION","NONSMOKING","TAXESINCLUDED"],"cancellationPolicy":{"canxDays":1,"freeCancellationEnabled":true}},"taxes":[],"hoscars":{"awards":[],"nominations":[]},"facilities":[{"name":"FACILITYCATEGORYFREE","id":1,"facilities":[{"id":80,"name":"FREECITYMAPS"},{"id":90,"name":"FREEWIFI"},{"id":103,"name":"FREEINTERNETACCESS"}]},{"name":"FACILITYCATEGORYGENERAL","id":2,"facilities":[{"id":28,"name":"BICYCLEPARKING"}]},{"name":"FACILITYCATEGORYSERVICES","id":3,"facilities":[{"id":15,"name":"LUGGAGESTORAGE"},{"id":19,"name":"FAXSERVICE"},{"id":77,"name":"ATM"},{"id":121,"name":"HOUSEKEEPING"},{"id":129,"name":"CARDPHONES"},{"id":153,"name":"RECEPTIONLIMITEDHOURS"}]},{"name":"FACILITYCATEGORYENTERTAINMENT","id":5,"facilities":[{"id":4,"name":"INTERNETACCESS"},{"id":79,"name":"BOOKEXCHANGE"},{"id":133,"name":"WIFI"}]},{"name":"FACILITYCATEGORYFOODANDDRINKS","id":4,"facilities":[{"id":2,"name":"RESTAURANT"},{"id":12,"name":"BAR"},{"id":83,"name":"MEALSAVAILABLE"},{"id":117,"name":"CAFE"}]},{"name":"FACILITYCATEGORYKITCHEN","id":6,"facilities":[{"id":92,"name":"KITCHEN"}]},{"name":"FACILITYCATEGORYACCESSIBILITY","id":7,"facilities":[{"id":8,"name":"WHEELCHAIRACCESSIBLE"},{"id":27,"name":"ELEVATOR"}]},{"name":"FACILITYCATEGORYLAUNDRY","id":8,"facilities":[{"id":5,"name":"LAUNDRYFACILITIES"},{"id":102,"name":"DRYER"},{"id":131,"name":"WASHINGMACHINE"}]},{"name":"FACILITYCATEGORYWELLNESS","id":9,"facilities":[{"id":81,"name":"HOTSHOWERS"}]},{"name":"FACILITYCATEGORYSAFETYANDSECURITY","id":11,"facilities":[{"id":22,"name":"KEYCARDACCESS"},{"id":112,"name":"24HOURSECURITY"}]},{"name":"FACILITYCATEGORYSOCIALAREAS","id":12,"facilities":[{"id":24,"name":"COMMONROOM"}]},{"name":"FACILITYCATEGORYBEDROOM","id":13,"facilities":[{"id":9,"name":"LINENINCLUDED"},{"id":119,"name":"HAIRDRYERS"},{"id":132,"name":"TOWELSNOTINCLUDED"}]},{"name":"FACILITYCATEGORYAVAILABLEFORAFEE","id":15,"facilities":[{"id":13,"name":"TOWELSFORHIRE"},{"id":115,"name":"HAIRDRYERSFORHIRE"}]}],"images":[{"prefix":"a.hwstatic.com/image/upload/f_auto,q_auto","suffix":"/v1/propertyimages/4/4038/xuftisqfwmfsod5fig97","position":1},{"prefix":"a.hwstatic.com/image/upload/f_auto,q_auto","suffix":"/v1/propertyimages/4/4038/fwduoer2cizqtfqlnmsx","position":2},{"prefix":"a.hwstatic.com/image/upload/f_auto,q_auto","suffix":"/v1/propertyimages/4/4038/vy4dvugoorgkx206wpl2","position":3},{"prefix":"a.hwstatic.com/image/upload/f_auto,q_auto","suffix":"/v1/propertyimages/4/4038/jicmhnntur41k8a9493e","position":7},{"prefix":"a.hwstatic.com/image/upload/f_auto,q_auto","suffix":"/v1/propertyimages/4/4038/qtadgitzuad80bpnxdyh","position":8},{"prefix":"a.hwstatic.com/image/upload/f_auto,q_auto","suffix":"/v1/propertyimages/4/4038/brlv67rxfzibjfgadaod","position":9},{"prefix":"a.hwstatic.com/image/upload/f_auto,q_auto","suffix":"/v1/propertyimages/4/4038/krpombb5jqhghjz83iud","position":10},{"prefix":"a.hwstatic.com/image/upload/f_auto,q_auto","suffix":"/v1/propertyimages/4/4038/l4nznxf8icp8gucg66di","position":11},{"prefix":"a.hwstatic.com/image/upload/f_auto,q_auto","suffix":"/v1/propertyimages/4/4038/cpgcyqjcybf814fatlml","position":12},{"prefix":"a.hwstatic.com/image/upload/f_auto,q_auto","suffix":"/v1/propertyimages/4/4038/ra7krndajt9hnhhdjjex","position":13},{"prefix":"a.hwstatic.com/image/upload/f_auto,q_auto","suffix":"/v1/propertyimages/4/4038/bo6wcojkt4491uaih8fp","position":14},{"prefix":"a.hwstatic.com/image/upload/f_auto,q_auto","suffix":"/v1/propertyimages/4/4038/qfgnfydzgrmohndoaojp","position":15},{"prefix":"a.hwstatic.com/image/upload/f_auto,q_auto","suffix":"/v1/propertyimages/4/4038/la1pqg6tgalfpcdliuud","position":16},{"prefix":"a.hwstatic.com/image/upload/f_auto,q_auto","suffix":"/v1/propertyimages/4/4038/tdjwqwwsqxn9gqszayhk","position":17},{"prefix":"a.hwstatic.com/image/upload/f_auto,q_auto","suffix":"/v1/propertyimages/4/4038/qcqgpwn5hysr14jilpkj","position":18},{"prefix":"a.hwstatic.com/image/upload/f_auto,q_auto","suffix":"/v1/propertyimages/4/4038/iop6dvcdosafml98qazr","position":19}],"videos":[],"video":null,"payments":{"payNow":false},"paymentMethods":["Visa","Mastercard","VisaDebit","Electron","Maestro","JCB"],"hostelworldRecommends":false,"isElevateProperty":false,"hasExperiences":false,"timesBookedToday":3,"promotions":[],"categories":[]}
